keylight_cli/__init__.py
keylight_cli/keylight_cli.py
keylight_cli-0.1.3.dist-info/entry_points.txt
keylight_cli-0.1.3.dist-info/WHEEL
keylight_cli-0.1.3.dist-info/METADATA
keylight_cli-0.1.3.dist-info/RECORD
